diagram.py
diagram-0.2.28.data/scripts/diagram
diagram-0.2.28.dist-info/LICENSE.md
diagram-0.2.28.dist-info/METADATA
diagram-0.2.28.dist-info/WHEEL
diagram-0.2.28.dist-info/top_level.txt
diagram-0.2.28.dist-info/RECORD
