Metadata-Version: 2.1
Name: diagram
Version: 0.2.28
Summary: Text mode diagrams using UTF-8 characters and fancy colors
Home-page: https://github.com/tehmaze/diagram
Author: Wijnand Modderman-Lenstra
Author-email: maze@pyth0n.org
License: UNKNOWN
Keywords: diagram,graph,ascii,ansi,text
Platform: UNKNOWN
